math_pro/PyPyNum.png
math_pro/README.md
math_pro/__init__.py
math_pro-1.11.0.dist-info/METADATA
math_pro-1.11.0.dist-info/WHEEL
math_pro-1.11.0.dist-info/top_level.txt
math_pro-1.11.0.dist-info/RECORD
