Metadata-Version: 2.1
Name: math_pro
Version: 1.11.0
Summary: A multifunctional mathematical calculation package written in pure Python programming language [Python>=3.4] (It is an alias for PyPyNum)
Home-page: https://github.com/PythonSJL/PyPyNum
Author: Shen Jiayi
Author-email: 2261748025@qq.com
License: 
Keywords: math,数学,mathematics,数学计算,numerical,数值,computation,计算,scientific,科学,algebra,代数,calculus,微积分,statistics,统计,linear-algebra,线性代数,optimization,优化,numerical-analysis,数值分析,matrix,矩阵,vector,向量,tensor,张量,numerics,数值计算,library,库,tools,工具,utils,实用程序,algorithms,算法,software,软件,package,包,methods,方法,data-science,数据科学,machine-learning,机器学习,computational,计算的,operations,操作,functions,函数,processing,处理,programming,编程,simulation,仿真,visualization,可视化,physics,物理
Requires-Python: >=3.4
Requires-Dist: pypynum
